LICENSE
MANIFEST.in
README.md
setup.cfg
setup.py
docassemble/__init__.py
docassemble.LAWVRelease.egg-info/PKG-INFO
docassemble.LAWVRelease.egg-info/SOURCES.txt
docassemble.LAWVRelease.egg-info/dependency_links.txt
docassemble.LAWVRelease.egg-info/namespace_packages.txt
docassemble.LAWVRelease.egg-info/not-zip-safe
docassemble.LAWVRelease.egg-info/top_level.txt
docassemble/LAWVRelease/__init__.py
docassemble/LAWVRelease/data/questions/lawv_release.yml
docassemble/LAWVRelease/data/sources/README.md
docassemble/LAWVRelease/data/static/README.md
docassemble/LAWVRelease/data/static/cps_release.png
docassemble/LAWVRelease/data/static/fast_release.png
docassemble/LAWVRelease/data/static/fast_represent.png
docassemble/LAWVRelease/data/static/lawv_release.png
docassemble/LAWVRelease/data/static/lis_release.png
docassemble/LAWVRelease/data/static/voca_release.png
docassemble/LAWVRelease/data/templates/README.md
docassemble/LAWVRelease/data/templates/cps_release.pdf
docassemble/LAWVRelease/data/templates/fast_release.pdf
docassemble/LAWVRelease/data/templates/fast_represent.pdf
docassemble/LAWVRelease/data/templates/lawv_release.pdf
docassemble/LAWVRelease/data/templates/lis_release.pdf
docassemble/LAWVRelease/data/templates/voca_release.pdf