Metadata-Version: 2.1
Name: docassemble.LAWVRelease
Version: 1.0.6
Summary: A docassemble extension for a multi-part interview for creating one of 5 releases (LAWV General, VOCA {Victims of Crime Act}, DHHR CPS, Lawyer in the School, and FAST).
Home-page: https://docassemble.org
Author: System Administrator
Author-email: dhenry@lawv.net
License: The MIT License (MIT)
Platform: UNKNOWN
License-File: LICENSE
